{
    "type" : "plugin",
    "platform" : "python",
    "sub_platforms" : ["cpython"],
    "id" : "pt.hive.colony.plugins.data.entity_manager_helper",
    "name" : "Entity Manager Helper Plugin",
    "short_name" : "Entity Manager Helper",
    "description" : "Entity Manager Helper Plugin",
    "version" : "1.0.0",
    "author" : "Hive Solutions Lda. <development@hive.pt>",
    "capabilities" : ["entity_manager_helper", "build_automation_item"],
    "capabilities_allowed" : [],
    "dependencies" : [{
                "id" : "pt.hive.colony.plugins.data.entity_manager.new",
                "version" : "1.x.x"
            }, {
                "id" : "pt.hive.colony.plugins.business.helper",
                "version" : "1.x.x"
            }],
    "main_file" : "entity_manager_helper_plugin.py",
    "resources" : ["entity_manager_helper_plugin.py", "data/__init__.py",
            "data/entity_manager_helper/__init__.py",
            "data/entity_manager_helper/entity_manager_helper_system.py",
            "data/entity_manager_helper/resources/baf.xml"],
    "extra_resources" : ["entity_manager_helper_plugin.pyc",
            "data/__init__.pyc", "data/entity_manager_helper/__init__.pyc",
            "data/entity_manager_helper/entity_manager_helper_system.pyc"]
}
